hurricane/__init__.py
hurricane/amqp/__init__.py
hurricane/amqp/basehandler.py
hurricane/amqp/loggers.py
hurricane/amqp/worker.py
hurricane/management/__init__.py
hurricane/management/commands/__init__.py
hurricane/management/commands/consume.py
hurricane/management/commands/serve.py
hurricane/metrics/__init__.py
hurricane/metrics/base.py
hurricane/metrics/exceptions.py
hurricane/metrics/registry.py
hurricane/metrics/requests.py
hurricane/server/__init__.py
hurricane/server/debugging.py
hurricane/server/django.py
hurricane/server/exceptions.py
hurricane/server/loggers.py
hurricane/server/wsgi.py
hurricane/testing/__init__.py
hurricane/testing/actors.py
hurricane/testing/drivers.py
hurricane/testing/start_webhook_receiver.py
hurricane/testing/testcases.py
hurricane/webhooks/__init__.py
hurricane/webhooks/base.py
hurricane/webhooks/exceptions.py
hurricane/webhooks/registry.py
hurricane/webhooks/webhook_types.py
django_hurricane-1.6.1.dist-info/METADATA
django_hurricane-1.6.1.dist-info/WHEEL
django_hurricane-1.6.1.dist-info/licenses/LICENSE
django_hurricane-1.6.1.dist-info/RECORD
