Metadata-Version: 2.4
Name: django-hurricane
Version: 1.6.1
Summary: A Kubernetes Native Stack Specifically Created For Django
License: MIT
License-File: LICENSE
Keywords: django,kubernetes,hurricane
Author: Michael Schilonka
Author-email: michael@blueshoe.io
Requires-Python: >=3.9,<4.0
Classifier: Environment :: Web Environment
Classifier: Framework :: Django
Classifier: Framework :: Django :: 2.2
Classifier: Framework :: Django :: 3.2
Classifier: Framework :: Django :: 4.2
Classifier: Intended Audience :: Developers
Classifier: License :: OSI Approved :: MIT License
Classifier: Programming Language :: Python :: 3
Classifier: Programming Language :: Python :: 3.9
Classifier: Programming Language :: Python :: 3.10
Classifier: Programming Language :: Python :: 3.11
Classifier: Programming Language :: Python :: 3.12
Classifier: Programming Language :: Python :: 3.13
Classifier: Programming Language :: Python :: 3.14
Classifier: Topic :: Software Development
Classifier: Topic :: Software Development :: Build Tools
Classifier: Topic :: Software Development :: Libraries :: Python Modules
Requires-Dist: django (>=2.2)
Requires-Dist: pika (>=1.3.2,<2.0.0)
Requires-Dist: prometheus-client (>=0.17.1,<0.18.0)
Requires-Dist: psutil (>=5.9.8,<6.0.0)
Requires-Dist: requests (>=2.25)
Requires-Dist: tornado (>=6.3.3,<7.0.0)
Project-URL: Documentation, https://django-hurricane.readthedocs.io/en/latest/
Project-URL: Homepage, https://django-hurricane.io/
Project-URL: Repository, https://github.com/django-hurricane/django-hurricane
